yellowdog_airflow_provider-1.0.1.dist-info/licenses/LICENSE
yellowdog_provider/__init__.py
yellowdog_provider/exceptions/__init__.py
yellowdog_provider/exceptions/yellowdog_exceptions.py
yellowdog_provider/hooks/__init__.py
yellowdog_provider/hooks/yellowdog_hooks.py
yellowdog_provider/operators/__init__.py
yellowdog_provider/operators/yellowdog_operators.py
yellowdog_provider/sensors/__init__.py
yellowdog_provider/sensors/yellowdog_sensors.py
yellowdog_provider/utils/__init__.py
yellowdog_provider/utils/yellowdog_utils.py
yellowdog_airflow_provider-1.0.1.dist-info/METADATA
yellowdog_airflow_provider-1.0.1.dist-info/WHEEL
yellowdog_airflow_provider-1.0.1.dist-info/entry_points.txt
yellowdog_airflow_provider-1.0.1.dist-info/top_level.txt
yellowdog_airflow_provider-1.0.1.dist-info/RECORD
