Metadata-Version: 2.4
Name: yellowdog-airflow-provider
Version: 1.0.1
Summary: YellowDog Provider for Apache Airflow.
Author-email: YellowDog Limited <support@yellowdog.co>
License-Expression: Apache-2.0
Project-URL: Homepage, https://github.com/yellowdog/airflow-provider
Project-URL: Source, https://github.com/yellowdog/airflow-provider
Classifier: Programming Language :: Python :: 3.10
Classifier: Programming Language :: Python :: 3.11
Classifier: Programming Language :: Python :: 3.12
Classifier: Operating System :: OS Independent
Classifier: Development Status :: 4 - Beta
Classifier: Framework :: Apache Airflow
Classifier: Framework :: Apache Airflow :: Provider
Requires-Python: <3.13,>=3.10
License-File: LICENSE
Requires-Dist: apache-airflow>=2.10.0
Requires-Dist: yellowdog-sdk>=9.1.4
Dynamic: license-file
